foobar.py
sunspot.py
test.py
sunspot-0.71.dist-info/METADATA
sunspot-0.71.dist-info/WHEEL
sunspot-0.71.dist-info/top_level.txt
sunspot-0.71.dist-info/RECORD
