Metadata-Version: 2.1
Name: sunspot
Version: 0.71
Summary: Simple and light-weight JPL ephemeris parser and tracking engine for astronomy and telescope guidance. Provides simple lists of ephemeris data for any Target Body available through the JPL Horizons App. Also provides real-time tracking of those data for the duration of an ephemeris.
Author-email: Phillip Curtsmith <phillip.curtsmith@gmail.com>
Project-URL: Homepage, https://pypi.org/project/sunspot/
Project-URL: Bug Tracker, https://github.com/phillipcurtsmith/sunspot-issues/issues
Classifier: Programming Language :: Python :: 3
Classifier: License :: OSI Approved :: GNU General Public License v3 (GPLv3)
Classifier: Operating System :: OS Independent
Classifier: Development Status :: 3 - Alpha
Classifier: Intended Audience :: Developers
Classifier: Intended Audience :: Education
Classifier: Intended Audience :: End Users/Desktop
Classifier: Intended Audience :: Science/Research
Classifier: Natural Language :: English
